mochi/__init__.py
mochi/auth.py
mochi/cards.py
mochi/client.py
mochi/constant.py
mochi/decks.py
mochi/models.py
mochi/template.py
mochi_api_client-0.1.4.dist-info/LICENSE
mochi_api_client-0.1.4.dist-info/METADATA
mochi_api_client-0.1.4.dist-info/WHEEL
mochi_api_client-0.1.4.dist-info/RECORD
