Metadata-Version: 2.1
Name: mochi-api-client
Version: 0.1.4
Summary: Python wrapper for the Mochi spaced repetition platform API
Home-page: https://github.com/gsejas/mochi-api-client
License: MIT
Keywords: mochi,api,client,wrapper,spaced repetition
Author: GSejas
Author-email: jsequeira03@gmail.com
Requires-Python: >=3.10,<4.0
Classifier: Development Status :: 3 - Alpha
Classifier: Intended Audience :: Developers
Classifier: License :: OSI Approved :: MIT License
Classifier: Programming Language :: Python :: 3
Classifier: Programming Language :: Python :: 3.10
Classifier: Programming Language :: Python :: 3.11
Classifier: Programming Language :: Python :: 3.12
Classifier: Programming Language :: Python :: 3.13
Classifier: Programming Language :: Python :: 3.6
Classifier: Programming Language :: Python :: 3.7
Classifier: Programming Language :: Python :: 3.8
Classifier: Programming Language :: Python :: 3.9
Classifier: Topic :: Software Development :: Libraries :: Python Modules
Requires-Dist: requests (>=2.32.3,<3.0.0)
Project-URL: Repository, https://github.com/gsejas/mochi-api-client
